{
  "Dallas": [
    32.78, 
    -96.8
  ], 
  "Philadelphia": [
    39.952, 
    -75.164
  ], 
  "Denver": [
    39.739, 
    -104.985
  ], 
  "San Francisco": [
    37.779, 
    -122.419
  ], 
  "Phoenix": [
    33.448, 
    -112.074
  ], 
  "Pittsburgh": [
    40.442, 
    -79.99
  ], 
  "Sacramento": [
    38.582, 
    -121.494
  ], 
  "San Diego": [
    32.747, 
    -117.212
  ], 
  "Los Angeles": [
    34.05, 
    -118.242
  ], 
  "Atlanta": [
    33.749, 
    -84.39
  ], 
  "San Antonio": [
    29.425, 
    -98.495
  ], 
  "Tampa": [
    27.948, 
    -82.458
  ], 
  "Charlotte": [
    38.029, 
    -78.477
  ], 
  "Miami": [
    25.788, 
    -80.127
  ], 
  "Detroit": [
    42.332, 
    -83.047
  ], 
  "Baltimore": [
    39.281, 
    -76.568
  ], 
  "St. Louis": [
    38.626, 
    -90.199
  ], 
  "Houston": [
    29.878, 
    -95.531
  ], 
  "Boston": [
    42.36, 
    -71.06
  ], 
  "Washington": [
    38.895, 
    -77.036
  ], 
  "Minneapolis": [
    44.977, 
    -93.265
  ], 
  "New York": [
    40.731, 
    -73.987
  ], 
  "Chicago": [
    41.876, 
    -87.624
  ], 
  "Portland": [
    43.661, 
    -70.255
  ], 
  "Seattle": [
    47.599, 
    -122.329
  ]
}